lemon/__init__.py
lemon/explainer.py
lemon/explanation.py
lemon/kernels.py
tests/__init__.py
tests/test_explainer.py
lemon_explainer_research_use-1.0.0.dist-info/LICENSE
lemon_explainer_research_use-1.0.0.dist-info/METADATA
lemon_explainer_research_use-1.0.0.dist-info/WHEEL
lemon_explainer_research_use-1.0.0.dist-info/top_level.txt
lemon_explainer_research_use-1.0.0.dist-info/RECORD
