Metadata-Version: 2.1
Name: lemon-explainer-research-use
Version: 1.0.0
Summary: lemon-explainer package updated for research usages.
Author: Dennis Collaris
Maintainer: Mohammad Amin Dadgar
Maintainer-email: dadgaramin96@gmail.com
License-File: LICENSE
Requires-Dist: numpy
Requires-Dist: pandas
Requires-Dist: matplotlib
